Workbook
Name Slicer_Language: #N/A

Sheet IMDB_Movies
A1: Movie Name | B1: Director | C1: Genre | D1: Language | E1: Duration | F1: IMDB Score | G1: Budget | H1: Gross | I1: Profit Margin
A2: Avatar | B2: James Cameron | C2: Action | D2: English | E2: 178 | F2: 7.9 | G2: 237000000 | H2: 760505847 | I2: =IMDB_Movies!$H2-IMDB_Movies!$G2 -> 523505847
A3: Pirates of the Caribbean: At World's End | B3: Gore Verbinski | C3: Action | D3: English | E3: 169 | F3: 7.1 | G3: 300000000 | H3: 309404152 | I3: =IMDB_Movies!$H3-IMDB_Movies!$G3 -> 9404152
A4: Spectre | B4: Sam Mendes | C4: Action | D4: English | E4: 148 | F4: 6.8 | G4: 245000000 | H4: 200074175 | I4: =IMDB_Movies!$H4-IMDB_Movies!$G4 -> -44925825
A5: The Dark Knight Rises | B5: Christopher Nolan | C5: Action | D5: English | E5: 164 | F5: 8.5 | G5: 250000000 | H5: 448130642 | I5: =IMDB_Movies!$H5-IMDB_Movies!$G5 -> 198130642
A6: John Carter | B6: Andrew Stanton | C6: Action | D6: English | E6: 132 | F6: 6.6 | G6: 263700000 | H6: 73058679 | I6: =IMDB_Movies!$H6-IMDB_Movies!$G6 -> -190641321
A7: Spider-Man 3 | B7: Sam Raimi | C7: Action | D7: English | E7: 156 | F7: 6.2 | G7: 258000000 | H7: 336530303 | I7: =IMDB_Movies!$H7-IMDB_Movies!$G7 -> 78530303
A8: Tangled | B8: Nathan Greno | C8: Adventure | D8: English | E8: 100 | F8: 7.8 | G8: 260000000 | H8: 200807262 | I8: =IMDB_Movies!$H8-IMDB_Movies!$G8 -> -59192738
A9: Avengers: Age of Ultron | B9: Joss Whedon | C9: Action | D9: English | E9: 141 | F9: 7.5 | G9: 250000000 | H9: 458991599 | I9: =IMDB_Movies!$H9-IMDB_Movies!$G9 -> 208991599
A10: Harry Potter and the Half-Blood Prince | B10: David Yates | C10: Adventure | D10: English | E10: 153 | F10: 7.5 | G10: 250000000 | H10: 301956980 | I10: =IMDB_Movies!$H10-IMDB_Movies!$G10 -> 51956980
A11: Batman v Superman: Dawn of Justice | B11: Zack Snyder | C11: Action | D11: English | E11: 183 | F11: 6.9 | G11: 250000000 | H11: 330249062 | I11: =IMDB_Movies!$H11-IMDB_Movies!$G11 -> 80249062
A12: Superman Returns | B12: Bryan Singer | C12: Action | D12: English | E12: 169 | F12: 6.1 | G12: 209000000 | H12: 200069408 | I12: =IMDB_Movies!$H12-IMDB_Movies!$G12 -> -8930592
A13: Quantum of Solace | B13: Marc Forster | C13: Action | D13: English | E13: 106 | F13: 6.7 | G13: 200000000 | H13: 168368427 | I13: =IMDB_Movies!$H13-IMDB_Movies!$G13 -> -31631573
... A4791: My Date with Drew | B4791: Jon Gunn | C4791: Documentary | D4791: English | E4791: 90 | F4791: 6.6 | G4791: 1100 | H4791: 85222 | I4791: =IMDB_Movies!$H4791-IMDB_Movies!$G4791 -> 84122

Sheet Movie Genre Analysis
A2: Genre | B2: Count of IMDB Score | C2: Average of IMDB Score | D2: Var of IMDB Score | E2: StdDevp of IMDB Score | F2: Min of IMDB Score | G2: Max of IMDB Score | H2: Range of IMDB Score | J2: Genre | K2: Count of IMDB Score
A3: Action | B3: 1090 | C3: 6.2090826 | D3: 1.2218366 | E3: 1.10486 | F3: 1.7 | G3: 9 | H3: =G3-F3 -> 7.3 | J3: Action | K3: 1090
A4: Adventure | B4: 435 | C4: 6.5193103 | D4: 1.2763083 | E4: 1.1284388 | F4: 2.3 | G4: 8.6 | H4: =G4-F4 -> 6.3 | J4: Adventure | K4: 435
A5: Animation | B5: 57 | C5: 6.5403509 | D5: 1.3742356 | E5: 1.1619493 | F5: 3.7 | G5: 8.4 | H5: =G5-F5 -> 4.7 | J5: Animation | K5: 57
A6: Biography | B6: 249 | C6: 7.1554217 | D6: 0.48489992 | E6: 0.69494786 | F6: 4.5 | G6: 8.9 | H6: =G6-F6 -> 4.4 | J6: Biography | K6: 249
A7: Comedy | B7: 1278 | C7: 6.163928 | D7: 1.1458004 | E7: 1.0700018 | F7: 1.9 | G7: 9.5 | H7: =G7-F7 -> 7.6 | J7: Comedy | K7: 1278
A8: Crime | B8: 319 | C8: 6.8526646 | D8: 0.88564539 | E8: 0.93961113 | F8: 3.1 | G8: 9.3 | H8: =G8-F8 -> 6.2 | J8: Crime | K8: 319
A9: Documentary | B9: 81 | C9: 7.1592593 | D9: 1.4364444 | E9: 1.1910964 | F9: 1.6 | G9: 8.7 | H9: =G9-F9 -> 7.1 | J9: Documentary | K9: 81
A10: Drama | B10: 913 | C10: 6.7452355 | D10: 0.97815984 | E10: 0.98847786 | F10: 2 | G10: 8.8 | H10: =G10-F10 -> 6.8 | J10: Drama | K10: 913
A11: Family | B11: 11 | C11: 5.7090909 | D11: 3.8709091 | E11: 1.875902 | F11: 2.8 | G11: 8.6 | H11: =G11-F11 -> 5.8 | J11: Family | K11: 11
A12: Fantasy | B12: 47 | C12: 6.3808511 | D12: 0.83592969 | E12: 0.9045131 | F12: 4.3 | G12: 7.9 | H12: =G12-F12 -> 3.6 | J12: Fantasy | K12: 47
A13: Film-Noir | B13: 1 | C13: 7.6 | D13: #DIV/0! | E13: 0 | F13: 7.6 | G13: 7.6 | H13: =G13-F13 -> 0 | J13: Film-Noir | K13: 1
A14: History | B14: 1 | C14: 7.5 | D14: #DIV/0! | E14: 0 | F14: 7.5 | G14: 7.5 | H14: =G14-F14 -> 0 | J14: History | K14: 1
A15: Horror | B15: 221 | C15: 5.6339367 | D15: 1.2371613 | E15: 1.1097582 | F15: 2.2 | G15: 8.5 | H15: =G15-F15 -> 6.3 | J15: Horror | K15: 221
A16: Music | B16: 1 | C16: 7.2 | D16: #DIV/0! | E16: 0 | F16: 7.2 | G16: 7.2 | H16: =G16-F16 -> 0 | J16: Music | K16: 1
A17: Musical | B17: 4 | C17: 6 | D17: 3.1666667 | E17: 1.5411035 | F17: 3.4 | G17: 7.2 | H17: =G17-F17 -> 3.8 | J17: Musical | K17: 4
A18: Mystery | B18: 32 | C18: 6.534375 | D18: 1.3132964 | E18: 1.1279432 | F18: 3.2 | G18: 8.5 | H18: =G18-F18 -> 5.3 | J18: Mystery | K18: 32
A19: Romance | B19: 4 | C19: 6.275 | D19: 0.64916667 | E19: 0.69776429 | F19: 5.2 | G19: 7.1 | H19: =G19-F19 -> 1.9 | J19: Romance | K19: 4
A20: Sci-Fi | B20: 13 | C20: 6 | D20: 2.2116667 | E20: 1.4288242 | F20: 2.8 | G20: 8.2 | H20: =G20-F20 -> 5.4 | J20: Sci-Fi | K20: 13
A21: Thriller | B21: 21 | C21: 5.5809524 | D21: 1.773619 | E21: 1.2996773 | F21: 3.4 | G21: 8.1 | H21: =G21-F21 -> 4.7 | J21: Thriller | K21: 21
A22: Western | B22: 12 | C22: 6.5833333 | D22: 2.559697 | E22: 1.5317927 | F22: 3.8 | G22: 8.9 | H22: =G22-F22 -> 5.1 | J22: Western | K22: 12

Sheet Movie Duration Analysis
J3: Descriptive Statistics for Movie duration
J4: MEAN | K4: =AVERAGE(Table1[Duration]) -> 108.05992
J5: MEDIAN | K5: =MEDIAN(Table1[Duration]) -> 104
J6: STANDARD DEVIATION | K6: =_xlfn.STDEV.P(Table1[Duration]) -> 22.584362
C17: AS THE DURATION INCREASES, MOVIES TEND TO SCORE HIGH IMBD RATINGS

Sheet Language Analysis
A2: Language | B2: Count of Movie Name | C2: Average of IMDB Score | D2: StdDevp of IMDB Score | F2: TOP 3 MOVIES | H2: AVG | I2: STD
A3: Aboriginal | B3: 2 | C3: 6.95 | D3: 0.55 | F3: {=_xlfn._xlws.SORT(_xlfn._xlws.FILTER(A3:D46,(B3:B46>=PERCENTILE(B3:B46,0.95))),2,-1)} -> English | G3: 4479 | H3: 6.3707747 | I3: 1.114335
A4: Arabic | B4: 5 | C4: 7.38 | D4: 0.7909488 | F4: French | G4: 72 | H4: 7.0208333 | I4: 0.71140266
A5: Aramaic | B5: 1 | C5: 7.1 | D5: 0 | F5: Spanish | G5: 40 | H5: 6.9375 | I5: 0.84430075
A6: Bosnian | B6: 1 | C6: 4.3 | D6: 0
A7: Cantonese | B7: 11 | C7: 6.9545455 | D7: 0.67198977
A8: Chinese | B8: 3 | C8: 5.6666667 | D8: 0.44969125 | F8: 94% OF MOVIES ARE PRODUCED IN ENGLISH LANGUAGE
A9: Czech | B9: 1 | C9: 7.4 | D9: 0
A10: Danish | B10: 5 | C10: 7.5 | D10: 0.96332757
A11: Dari | B11: 2 | C11: 7.5 | D11: 0.1
A12: Dutch | B12: 4 | C12: 7.425 | D12: 0.37666298
A13: Dzongkha | B13: 1 | C13: 7.5 | D13: 0
A14: English | B14: 4479 | C14: 6.3707747 | D14: 1.114335
A15: Filipino | B15: 1 | C15: 6.7 | D15: 0
A16: French | B16: 72 | C16: 7.0208333 | D16: 0.71140266
A17: German | B17: 19 | C17: 7.3421053 | D17: 0.92867522
A18: Greek | B18: 1 | C18: 7.3 | D18: 0
A19: Hebrew | B19: 5 | C19: 7.58 | D19: 0.29933259
A20: Hindi | B20: 27 | C20: 6.7740741 | D20: 1.1802676
... A47: Grand Total | B47: 4790 | C47: 6.413904 | D47: 1.1156145

Sheet Director Analysis
A2: Director | B2: Average of IMDB Score | C2: StdDevp of IMDB Score | E2: 99th Percentile | F2: =PERCENTILE(B3:B2383,0.99) -> 8.3
A3: A. Raven Cruz | B3: 1.9 | C3: 0
A4: Aaron Hann | B4: 6 | C4: 0 | E4: {=_xlfn._xlws.SORT(_xlfn._xlws.FILTER(A3:B2383,(B3:B2383>=F2)),2,-1)} -> John Blanchard | F4: 9.5
A5: Aaron Schneider | B5: 7.1 | C5: 0 | E5: Cary Bell | F5: 8.7
A6: Aaron Seltzer | B6: 2.7 | C6: 0 | E6: Mitchell Altieri | F6: 8.7
A7: Abel Ferrara | B7: 6.6 | C7: 0 | E7: Sadyk Sher-Niyaz | F7: 8.7
A8: Adam Brooks | B8: 7.2 | C8: 0 | E8: Charles Chaplin | F8: 8.6
A9: Adam Carolla | B9: 6.1 | C9: 0 | E9: Mike Mayhall | F9: 8.6
A10: Adam Goldberg | B10: 5.4 | C10: 0 | E10: Damien Chazelle | F10: 8.5
A11: Adam Green | B11: 5.7 | C11: 0 | E11: Majid Majidi | F11: 8.5
A12: Adam Jay Epstein | B12: 3.8 | C12: 0 | E12: Raja Menon | F12: 8.5
A13: Adam Marcus | B13: 4.3 | C13: 0 | E13: Sergio Leone | F13: 8.475
A14: Adam Mckay | B14: 6.9166667 | C14: 0.48102899 | E14: Tony Kaye | F14: 8.45
A15: Adam Rapp | B15: 6.4 | C15: 0 | E15: Christopher Nolan | F15: 8.425
A16: Adam Rifkin | B16: 6.5 | C16: 0.3 | E16: Asghar Farhadi | F16: 8.4
... A32: Alan J. Pakula | B32: 6.3 | C32: 0.2 | E32: Sut Jhally | F32: 8.3
A33: Alan Jacobs | B33: 7.3 | C33: 0
A34: Alan Metter | B34: 3.3 | C34: 0 | E34: TOTAL DIRECTORS | F34: =ROWS(F4:F32) -> 29
A35: Alan Parker | B35: 7.0333333 | C35: 0.52493386
A36: Alan Poul | B36: 5.3 | C36: 0 | E36: OVERALL CONTRIBUTION | F36: =SUM(F4:F32)/SUM(B3:B2383) -> 0.016540222
A37: Alan Rudolph | B37: 4.6 | C37: 0
A38: Alan Shapiro | B38: 5.2 | C38: 0
A39: Alan Taylor | B39: 6.85 | C39: 0.25
A40: Alan Yuen | B40: 6.2 | C40: 0
A41: Albert Brooks | B41: 5.6 | C41: 0
A42: Albert Hughes | B42: 7.0666667 | C42: 0.30912062
A43: Alec Asten | B43: 4.3 | C43: 0
A44: Alejandro Agresti | B44: 6.8 | C44: 0
A45: Alejandro Amenábar | B45: 7.15 | C45: 0.89582364
A46: Alejandro G. Iñárritu | B46: 7.7833333 | C46: 0.24776781
A47: Alejandro Monteverde | B47: 7.4 | C47: 0
A48: Aleksandr Veledinskiy | B48: 7.5 | C48: 0
... A2384: Grand Total | B2384: 6.413904 | C2384: 1.1156145

Sheet Budget Analysis
A2: CORRELATION COEFFICIENT | C2: =CORREL(Table1[Budget],Table1[Gross]) -> 0.23843551 | E2: Maximum Profit Margin | F2: =MAX(IMDB_Movies!I2:I4791) -> 523505847
E4: AVATAR MOVIE GAINED MAX PROFIT
